engineered_datasets/__init__.py
engineered_datasets/dataset.py
engineered_datasets-1.0a1.dist-info/METADATA
engineered_datasets-1.0a1.dist-info/WHEEL
engineered_datasets-1.0a1.dist-info/licenses/LICENSE
engineered_datasets-1.0a1.dist-info/RECORD
