Metadata-Version: 2.4
Name: engineered_datasets
Version: 1.0a1
Summary: Dataset generator utility for data science projects
Project-URL: Homepage, https://github.com/gperdrizet/datasets
Project-URL: Issues, https://github.com/gperdrizet/datasets/issues
Author-email: George Perdrizet <george@perdrizet.org>
License-Expression: GPL-3.0-or-later
License-File: LICENSE
Classifier: Operating System :: OS Independent
Classifier: Programming Language :: Python :: 3
Requires-Python: >=3.10
Requires-Dist: h5py
Requires-Dist: pandas
